ares_data/__init__.py
ares_data/ares_wrapper.py
ares_data/cznace.csv
ares_data/czso.py
ares_data/pocet_pracovniku.csv
ares_data-1.0.1.dist-info/METADATA
ares_data-1.0.1.dist-info/WHEEL
ares_data-1.0.1.dist-info/top_level.txt
ares_data-1.0.1.dist-info/RECORD
