Metadata-Version: 2.1
Name: ares-data
Version: 1.0.1
Summary: `ares_data` je Python light weight knihovna pro snadné získávání dat o společnostech z Českého obchodního rejstříku ARES.
Home-page: https://github.com/Newpaw/ares_data
Author: Jan Novopacký
Author-email: jan.novopacky@gmail.com
License: UNKNOWN
Platform: UNKNOWN
Classifier: Programming Language :: Python :: 3
Classifier: Programming Language :: Python :: 3.6
Classifier: Programming Language :: Python :: 3.7
Classifier: Programming Language :: Python :: 3.8
Classifier: Programming Language :: Python :: 3.9
Classifier: Programming Language :: Python :: 3.10
Classifier: License :: OSI Approved :: MIT License
Classifier: Operating System :: OS Independent
Requires-Python: >=3.6
Requires-Dist: bs4 >=0.0.1
Requires-Dist: requests >=2.25
